decisive_tree/__init__.py
decisive_tree/c45.py
decisive_tree/cart.py
decisive_tree/evaluation.py
decisive_tree/id3.py
decisive_tree/node_data.py
decisive_tree/preprocessing.py
decisive_tree-0.1.1.dist-info/licenses/LICENSE
decisive_tree-0.1.1.dist-info/METADATA
decisive_tree-0.1.1.dist-info/WHEEL
decisive_tree-0.1.1.dist-info/top_level.txt
decisive_tree-0.1.1.dist-info/RECORD
