Metadata-Version: 2.4
Name: decisive-tree
Version: 0.1.1
Summary: A collection of very decisive decision trees
Author-email: Mateus Diniz <mateushmdiniz@gmail.com>
License: MIT License
Project-URL: Homepage, https://github.com/mateushmd/decisive-tree
Project-URL: Bug Tracker, https://github.com/mateushmd/decisive-tree/issues
Classifier: Programming Language :: Python :: 3
Classifier: Operating System :: OS Independent
Requires-Python: >=3.11
License-File: LICENSE
Requires-Dist: numpy==2.3.3
Requires-Dist: pandas==2.3.2
Requires-Dist: treelib==1.8.0
Requires-Dist: matplotlib==3.10.6
Requires-Dist: seaborn==0.13.2
Dynamic: license-file
